django_dbconn_retry/__init__.py
django_dbconn_retry/apps.py
django_dbconn_retry/tests/__init__.py
django_dbconn_retry-0.1.9.dist-info/LICENSE
django_dbconn_retry-0.1.9.dist-info/METADATA
django_dbconn_retry-0.1.9.dist-info/WHEEL
django_dbconn_retry-0.1.9.dist-info/top_level.txt
django_dbconn_retry-0.1.9.dist-info/RECORD
