Metadata-Version: 2.1
Name: django-dbconn-retry
Version: 0.1.9
Summary: Patch Django to retry a database connection first before failing.
Home-page: https://github.com/jdelic/django-dbconn-retry/
Author: Jonas Maurus (@jdelic)
Author-email: jonas-dbconn-retry@gopythongo.com
Maintainer: GoPythonGo.com
Maintainer-email: info@gopythongo.com
Classifier: Development Status :: 4 - Beta
Classifier: Intended Audience :: Developers
Classifier: Intended Audience :: System Administrators
Classifier: Programming Language :: Python :: 3 :: Only
Classifier: License :: OSI Approved :: BSD License
Classifier: Operating System :: POSIX
License-File: LICENSE
